editini/__init__.py
editini/iniio.py
editini-1.0.5.dist-info/METADATA
editini-1.0.5.dist-info/WHEEL
editini-1.0.5.dist-info/top_level.txt
editini-1.0.5.dist-info/RECORD
