Metadata-Version: 2.1
Name: editini
Version: 1.0.5
Summary: It is easy to write and read .ini.  
Home-page: UNKNOWN
Author: Penguin0093
Author-email: 0093penguin@gmail.com
License: MIT
Platform: UNKNOWN
Classifier: Programming Language :: Python :: 3.7
Classifier: License :: OSI Approved :: MIT License
Classifier: Operating System :: OS Independent
